mod_ngarn/__init__.py
mod_ngarn/api.py
mod_ngarn/connection.py
mod_ngarn/utils.py
mod_ngarn/worker.py
mod_ngarn/schema/0001_init.sql
mod_ngarn-3.5.dist-info/entry_points.txt
mod_ngarn-3.5.dist-info/LICENSE
mod_ngarn-3.5.dist-info/WHEEL
mod_ngarn-3.5.dist-info/METADATA
mod_ngarn-3.5.dist-info/RECORD
