Metadata-Version: 2.1
Name: mod_ngarn
Version: 3.5
Summary: Simple async worker
Home-page: https://github.com/Proteus-tech/mod-ngarn
License: UNKNOWN
Author: Tle Ekkul
Author-email: e.aryuth@gmail.com
Requires-Python: ~=3.6
Classifier: License :: OSI Approved :: MIT License
Requires-Dist: asyncpg==0.18.3
Requires-Dist: Click==7.0
Requires-Dist: coverage==4.5.1; extra == "test"
Requires-Dist: pyre-check==0.0.16; extra == "test"
Requires-Dist: pytest==3.6.3; extra == "test"
Requires-Dist: pytest-asyncio==0.9.0; extra == "test"
Requires-Dist: pytest-cov==2.5.1; extra == "test"
Requires-Dist: pytest-icdiff==0.0.3; extra == "test"
Requires-Dist: freezegun==0.3.11; extra == "test"
Provides-Extra: test
